Metadata-Version: 2.1
Name: sc-mainwindow
Version: 1.1
Summary: scmainWindow is a pyqt5 custom widget that can be used as the main window
Home-page: https://github.com/SihinaCode/sc_mainwindow
Author: SihinaCode
License: MIT
Download-URL: https://github.com/SihinaCode/sc_mainwindow
Keywords: pyqt5,mainWindow,frameless
Platform: UNKNOWN
Classifier: Development Status :: 3 - Alpha
Classifier: Intended Audience :: Developers
Classifier: Topic :: Software Development :: Build Tools
Classifier: Programming Language :: Python :: 3
Classifier: Programming Language :: Python :: 3.5
Classifier: Programming Language :: Python :: 3.6
Classifier: Programming Language :: Python :: 3.7
Classifier: Programming Language :: Python :: 3.8
Classifier: Programming Language :: Python :: 3.9
